mythme/__init__.py
mythme/__main__.py
mythme/api/__init__.py
mythme/api/channels.py
mythme/api/credits.py
mythme/api/main.py
mythme/api/programs.py
mythme/api/queries.py
mythme/api/recordings.py
mythme/data/__init__.py
mythme/data/channels.py
mythme/data/credits.py
mythme/data/programs.py
mythme/data/queries.py
mythme/data/recordings.py
mythme/model/__init__.py
mythme/model/channel.py
mythme/model/config.py
mythme/model/credit.py
mythme/model/program.py
mythme/model/query.py
mythme/model/recording.py
mythme/model/setting.py
mythme/query/__init__.py
mythme/query/queries.py
mythme/ui/.DS_Store
mythme/ui/index.html
mythme/ui/assets/index-9qmwE1QI.css
mythme/ui/assets/index-Dpy4Pi-Q.js
mythme/ui/img/.DS_Store
mythme/ui/img/mm.png
mythme/utils/__init__.py
mythme/utils/config.py
mythme/utils/db.py
mythme/utils/log.py
mythme/utils/mythtv.py
mythme-0.0.8.dist-info/LICENSE
mythme-0.0.8.dist-info/METADATA
mythme-0.0.8.dist-info/WHEEL
mythme-0.0.8.dist-info/entry_points.txt
mythme-0.0.8.dist-info/top_level.txt
mythme-0.0.8.dist-info/RECORD
