Metadata-Version: 2.1
Name: mythme
Version: 0.0.8
Summary: Find and record programs on MythTV
License: MIT License
Project-URL: Homepage, https://github.com/donaldoakes/mythme#readme
Project-URL: Source, https://github.com/donaldoakes/mythme
Project-URL: Bug Reports, https://github.com/donaldoakes/mythme/issues
Keywords: mythtv,canned,search
Classifier: Development Status :: 5 - Production/Stable
Classifier: License :: OSI Approved :: MIT License
Classifier: Programming Language :: Python
Classifier: Programming Language :: Python :: 3.12
Classifier: Programming Language :: Python :: 3.13
Classifier: Programming Language :: Python :: 3
Requires-Python: >=3.12
License-File: LICENSE
Requires-Dist: annotated-types ==0.7.0
Requires-Dist: anyio ==4.6.2.post1
Requires-Dist: certifi ==2024.8.30
Requires-Dist: charset-normalizer ==3.4.0
Requires-Dist: click ==8.1.7
Requires-Dist: fastapi ==0.115.3
Requires-Dist: h11 ==0.14.0
Requires-Dist: httptools ==0.6.4
Requires-Dist: idna ==3.10
Requires-Dist: mariadb ==1.1.10
Requires-Dist: packaging ==24.1
Requires-Dist: pydantic ==2.9.2
Requires-Dist: pydantic-core ==2.23.4
Requires-Dist: python-dotenv ==1.0.1
Requires-Dist: PyYAML ==6.0.2
Requires-Dist: requests ==2.32.3
Requires-Dist: sniffio ==1.3.1
Requires-Dist: starlette ==0.41.0
Requires-Dist: typing-extensions ==4.12.2
Requires-Dist: urllib3 ==2.2.3
Requires-Dist: uvicorn ==0.32.0
Requires-Dist: uvloop ==0.21.0
Requires-Dist: watchfiles ==0.24.0
Requires-Dist: websockets ==13.1
